{"team":{"abbreviation":"LAL","full_name":"Los Angeles Lakers","id":1610612747},"season":"2025-26","ratings":{"def_rating":116.0,"off_rating":116.3,"net_rating":0.3,"pace":99.43,"def_rating_rank":22},"position_impact":{"G":{"sample_size":{"total_player_games":330,"unique_players":192},"deviations":{"PTS":{"value":0.194,"rank":17,"pctile":45},"REB":{"value":-0.294,"rank":2,"pctile":97},"AST":{"value":0.209,"rank":26,"pctile":14},"STL":{"value":0.053,"rank":23,"pctile":24},"BLK":{"value":-0.082,"rank":1,"pctile":100},"TOV":{"value":-0.027,"rank":15,"pctile":52},"FG_PCT":{"value":-0.001,"rank":24,"pctile":21},"FG3_PCT":{"value":-0.036,"rank":8,"pctile":76},"FGM":{"value":0.145,"rank":25,"pctile":17},"FGA":{"value":0.0,"rank":15,"pctile":52},"FG3M":{"value":0.022,"rank":18,"pctile":41},"FG3A":{"value":0.001,"rank":18,"pctile":41},"FTM":{"value":-0.12,"rank":8,"pctile":76},"FTA":{"value":-0.152,"rank":8,"pctile":76},"OREB":{"value":-0.105,"rank":2,"pctile":97},"DREB":{"value":-0.194,"rank":4,"pctile":90},"MIN":{"value":-0.255,"rank":10,"pctile":69}},"top_affected_players":[{"player_id":1629630,"player_name":"Ja Morant","team":"MEM","gp":2,"season_avg":{"PTS":19.5,"REB":3.3,"AST":8.1,"STL":1.0,"FG_PCT":0.41,"FG3_PCT":0.235},"vs_team_avg":{"PTS":12.0,"REB":2.0,"AST":9.0,"STL":1.5,"FG_PCT":0.313,"FG3_PCT":0.0},"deviations":{"PTS":-7.5,"REB":-1.3,"AST":0.9,"STL":0.5,"FG_PCT":-0.097,"FG3_PCT":-0.235}},{"player_id":1629656,"player_name":"Quentin Grimes","team":"PHI","gp":2,"season_avg":{"PTS":12.4,"REB":3.5,"AST":3.5,"STL":0.9,"FG_PCT":0.441,"FG3_PCT":0.348},"vs_team_avg":{"PTS":5.5,"REB":4.0,"AST":2.5,"STL":0.5,"FG_PCT":0.333,"FG3_PCT":0.143},"deviations":{"PTS":-6.9,"REB":0.5,"AST":-1.0,"STL":-0.4,"FG_PCT":-0.108,"FG3_PCT":-0.205}},{"player_id":1631157,"player_name":"Ryan Rollins","team":"MIL","gp":2,"season_avg":{"PTS":16.8,"REB":4.6,"AST":5.4,"STL":1.5,"FG_PCT":0.466,"FG3_PCT":0.411},"vs_team_avg":{"PTS":10.0,"REB":3.5,"AST":2.5,"STL":1.0,"FG_PCT":0.25,"FG3_PCT":0.1},"deviations":{"PTS":-6.8,"REB":-1.1,"AST":-2.9,"STL":-0.5,"FG_PCT":-0.216,"FG3_PCT":-0.311}},{"player_id":1630193,"player_name":"Immanuel Quickley","team":"TOR","gp":2,"season_avg":{"PTS":17.4,"REB":4.2,"AST":6.1,"STL":1.2,"FG_PCT":0.45,"FG3_PCT":0.379},"vs_team_avg":{"PTS":11.0,"REB":2.0,"AST":6.0,"STL":1.5,"FG_PCT":0.5,"FG3_PCT":0.375},"deviations":{"PTS":-6.4,"REB":-2.2,"AST":-0.1,"STL":0.3,"FG_PCT":0.05,"FG3_PCT":-0.004}},{"player_id":1628975,"player_name":"Jevon Carter","team":"ORL","gp":2,"season_avg":{"PTS":5.8,"REB":1.5,"AST":1.3,"STL":0.7,"FG_PCT":0.386,"FG3_PCT":0.388},"vs_team_avg":{"PTS":0.0,"REB":2.0,"AST":0.0,"STL":0.5,"FG_PCT":0.0,"FG3_PCT":0.0},"deviations":{"PTS":-5.8,"REB":0.5,"AST":-1.3,"STL":-0.2,"FG_PCT":-0.386,"FG3_PCT":-0.388}},{"player_id":1626164,"player_name":"Devin Booker","team":"PHX","gp":3,"season_avg":{"PTS":24.6,"REB":3.9,"AST":6.1,"STL":0.9,"FG_PCT":0.451,"FG3_PCT":0.313},"vs_team_avg":{"PTS":19.7,"REB":3.3,"AST":7.0,"STL":1.0,"FG_PCT":0.474,"FG3_PCT":0.111},"deviations":{"PTS":-4.9,"REB":-0.6,"AST":0.9,"STL":0.1,"FG_PCT":0.023,"FG3_PCT":-0.202}},{"player_id":1629001,"player_name":"De'Anthony Melton","team":"GSW","gp":2,"season_avg":{"PTS":12.4,"REB":2.8,"AST":2.4,"STL":1.5,"FG_PCT":0.411,"FG3_PCT":0.29},"vs_team_avg":{"PTS":7.5,"REB":0.5,"AST":2.5,"STL":2.5,"FG_PCT":0.227,"FG3_PCT":0.273},"deviations":{"PTS":-4.9,"REB":-2.3,"AST":0.1,"STL":1.0,"FG_PCT":-0.184,"FG3_PCT":-0.017}},{"player_id":1628368,"player_name":"De'Aaron Fox","team":"SAS","gp":3,"season_avg":{"PTS":18.6,"REB":3.8,"AST":6.2,"STL":1.2,"FG_PCT":0.481,"FG3_PCT":0.346},"vs_team_avg":{"PTS":14.0,"REB":3.0,"AST":4.7,"STL":1.7,"FG_PCT":0.421,"FG3_PCT":0.267},"deviations":{"PTS":-4.6,"REB":-0.8,"AST":-1.5,"STL":0.5,"FG_PCT":-0.06,"FG3_PCT":-0.079}},{"player_id":1629012,"player_name":"Collin Sexton","team":"CHI","gp":2,"season_avg":{"PTS":14.1,"REB":1.9,"AST":3.3,"STL":1.0,"FG_PCT":0.481,"FG3_PCT":0.378},"vs_team_avg":{"PTS":9.5,"REB":0.0,"AST":3.0,"STL":1.0,"FG_PCT":0.467,"FG3_PCT":0.2},"deviations":{"PTS":-4.6,"REB":-1.9,"AST":-0.3,"STL":0.0,"FG_PCT":-0.014,"FG3_PCT":-0.178}},{"player_id":1630545,"player_name":"Terrence Shannon Jr.","team":"MIN","gp":2,"season_avg":{"PTS":4.3,"REB":1.1,"AST":0.6,"STL":0.3,"FG_PCT":0.395,"FG3_PCT":0.395},"vs_team_avg":{"PTS":0.0,"REB":1.5,"AST":0.5,"STL":0.5,"FG_PCT":0.0,"FG3_PCT":0.0},"deviations":{"PTS":-4.3,"REB":0.4,"AST":-0.1,"STL":0.2,"FG_PCT":-0.395,"FG3_PCT":-0.395}},{"player_id":1642285,"player_name":"Cam Spencer","team":"MEM","gp":3,"season_avg":{"PTS":11.4,"REB":2.6,"AST":5.5,"STL":0.7,"FG_PCT":0.477,"FG3_PCT":0.443},"vs_team_avg":{"PTS":7.3,"REB":1.3,"AST":5.7,"STL":0.7,"FG_PCT":0.316,"FG3_PCT":0.25},"deviations":{"PTS":-4.1,"REB":-1.3,"AST":0.2,"STL":0.0,"FG_PCT":-0.161,"FG3_PCT":-0.193}},{"player_id":1642954,"player_name":"Will Richard","team":"GSW","gp":3,"season_avg":{"PTS":7.0,"REB":2.5,"AST":1.4,"STL":1.2,"FG_PCT":0.479,"FG3_PCT":0.349},"vs_team_avg":{"PTS":3.0,"REB":0.7,"AST":0.7,"STL":0.3,"FG_PCT":0.571,"FG3_PCT":0.333},"deviations":{"PTS":-4.0,"REB":-1.8,"AST":-0.7,"STL":-0.9,"FG_PCT":0.092,"FG3_PCT":-0.016}},{"player_id":1630170,"player_name":"Devin Vassell","team":"SAS","gp":3,"season_avg":{"PTS":14.6,"REB":3.9,"AST":2.4,"STL":0.9,"FG_PCT":0.444,"FG3_PCT":0.392},"vs_team_avg":{"PTS":10.7,"REB":3.0,"AST":3.3,"STL":1.7,"FG_PCT":0.379,"FG3_PCT":0.286},"deviations":{"PTS":-3.9,"REB":-0.9,"AST":0.9,"STL":0.8,"FG_PCT":-0.065,"FG3_PCT":-0.106}},{"player_id":1641712,"player_name":"Rayan Rupert","team":"MEM","gp":2,"season_avg":{"PTS":3.6,"REB":2.2,"AST":0.8,"STL":0.7,"FG_PCT":0.381,"FG3_PCT":0.318},"vs_team_avg":{"PTS":0.0,"REB":1.5,"AST":1.0,"STL":2.0,"FG_PCT":0.0,"FG3_PCT":0.0},"deviations":{"PTS":-3.6,"REB":-0.7,"AST":0.2,"STL":1.3,"FG_PCT":-0.381,"FG3_PCT":-0.318}},{"player_id":1642347,"player_name":"Jamal Shead","team":"TOR","gp":2,"season_avg":{"PTS":7.0,"REB":2.0,"AST":5.2,"STL":1.0,"FG_PCT":0.372,"FG3_PCT":0.325},"vs_team_avg":{"PTS":3.5,"REB":1.5,"AST":4.5,"STL":1.5,"FG_PCT":0.111,"FG3_PCT":0.167},"deviations":{"PTS":-3.5,"REB":-0.5,"AST":-0.7,"STL":0.5,"FG_PCT":-0.261,"FG3_PCT":-0.158}}],"label":"Guards"},"F":{"sample_size":{"total_player_games":313,"unique_players":179},"deviations":{"PTS":{"value":0.205,"rank":19,"pctile":38},"REB":{"value":-0.332,"rank":6,"pctile":83},"AST":{"value":0.086,"rank":20,"pctile":34},"STL":{"value":0.053,"rank":25,"pctile":17},"BLK":{"value":-0.105,"rank":1,"pctile":100},"TOV":{"value":-0.074,"rank":11,"pctile":66},"FG_PCT":{"value":0.014,"rank":27,"pctile":10},"FG3_PCT":{"value":-0.025,"rank":27,"pctile":10},"FGM":{"value":0.11,"rank":19,"pctile":38},"FGA":{"value":0.048,"rank":16,"pctile":48},"FG3M":{"value":0.027,"rank":19,"pctile":38},"FG3A":{"value":0.07,"rank":20,"pctile":34},"FTM":{"value":-0.042,"rank":13,"pctile":59},"FTA":{"value":-0.053,"rank":14,"pctile":55},"OREB":{"value":-0.089,"rank":5,"pctile":86},"DREB":{"value":-0.233,"rank":6,"pctile":83},"MIN":{"value":0.312,"rank":23,"pctile":24}},"top_affected_players":[{"player_id":1629675,"player_name":"Naz Reid","team":"MIN","gp":2,"season_avg":{"PTS":13.9,"REB":6.4,"AST":2.4,"STL":1.0,"FG_PCT":0.467,"FG3_PCT":0.381},"vs_team_avg":{"PTS":5.0,"REB":5.0,"AST":1.5,"STL":0.5,"FG_PCT":0.211,"FG3_PCT":0.222},"deviations":{"PTS":-8.9,"REB":-1.4,"AST":-0.9,"STL":-0.5,"FG_PCT":-0.256,"FG3_PCT":-0.159}},{"player_id":1626167,"player_name":"Myles Turner","team":"MIL","gp":2,"season_avg":{"PTS":12.5,"REB":5.6,"AST":1.6,"STL":0.7,"FG_PCT":0.442,"FG3_PCT":0.385},"vs_team_avg":{"PTS":5.5,"REB":7.0,"AST":0.5,"STL":0.0,"FG_PCT":0.4,"FG3_PCT":0.5},"deviations":{"PTS":-7.0,"REB":1.4,"AST":-1.1,"STL":-0.7,"FG_PCT":-0.042,"FG3_PCT":0.115}},{"player_id":1630168,"player_name":"Onyeka Okongwu","team":"ATL","gp":2,"season_avg":{"PTS":16.1,"REB":7.9,"AST":3.3,"STL":1.1,"FG_PCT":0.483,"FG3_PCT":0.385},"vs_team_avg":{"PTS":9.5,"REB":8.0,"AST":4.0,"STL":1.5,"FG_PCT":0.409,"FG3_PCT":0.0},"deviations":{"PTS":-6.6,"REB":0.1,"AST":0.7,"STL":0.4,"FG_PCT":-0.074,"FG3_PCT":-0.385}},{"player_id":1628398,"player_name":"Kyle Kuzma","team":"MIL","gp":2,"season_avg":{"PTS":12.9,"REB":4.8,"AST":2.6,"STL":0.6,"FG_PCT":0.483,"FG3_PCT":0.342},"vs_team_avg":{"PTS":7.0,"REB":2.0,"AST":1.0,"STL":0.5,"FG_PCT":0.313,"FG3_PCT":0.125},"deviations":{"PTS":-5.9,"REB":-2.8,"AST":-1.6,"STL":-0.1,"FG_PCT":-0.17,"FG3_PCT":-0.217}},{"player_id":1642843,"player_name":"Cooper Flagg","team":"DAL","gp":2,"season_avg":{"PTS":20.4,"REB":6.6,"AST":4.1,"STL":1.2,"FG_PCT":0.482,"FG3_PCT":0.302},"vs_team_avg":{"PTS":14.5,"REB":7.0,"AST":8.5,"STL":2.5,"FG_PCT":0.387,"FG3_PCT":0.25},"deviations":{"PTS":-5.9,"REB":0.4,"AST":4.4,"STL":1.3,"FG_PCT":-0.095,"FG3_PCT":-0.052}},{"player_id":1629655,"player_name":"Daniel Gafford","team":"DAL","gp":3,"season_avg":{"PTS":8.2,"REB":6.4,"AST":1.0,"STL":0.8,"FG_PCT":0.62,"FG3_PCT":0.0},"vs_team_avg":{"PTS":3.0,"REB":4.0,"AST":0.7,"STL":0.3,"FG_PCT":0.5,"FG3_PCT":0.0},"deviations":{"PTS":-5.2,"REB":-2.4,"AST":-0.3,"STL":-0.5,"FG_PCT":-0.12,"FG3_PCT":0.0}},{"player_id":1631096,"player_name":"Chet Holmgren","team":"OKC","gp":2,"season_avg":{"PTS":17.1,"REB":9.0,"AST":1.7,"STL":0.5,"FG_PCT":0.551,"FG3_PCT":0.346},"vs_team_avg":{"PTS":12.0,"REB":6.5,"AST":1.5,"STL":0.5,"FG_PCT":0.529,"FG3_PCT":0.5},"deviations":{"PTS":-5.1,"REB":-2.5,"AST":-0.2,"STL":0.0,"FG_PCT":-0.022,"FG3_PCT":0.154}},{"player_id":1641729,"player_name":"Brice Sensabaugh","team":"UTA","gp":3,"season_avg":{"PTS":12.7,"REB":3.0,"AST":1.6,"STL":0.7,"FG_PCT":0.446,"FG3_PCT":0.345},"vs_team_avg":{"PTS":7.7,"REB":2.3,"AST":1.0,"STL":0.7,"FG_PCT":0.304,"FG3_PCT":0.313},"deviations":{"PTS":-5.0,"REB":-0.7,"AST":-0.6,"STL":0.0,"FG_PCT":-0.142,"FG3_PCT":-0.032}},{"player_id":1630545,"player_name":"Terrence Shannon Jr.","team":"MIN","gp":2,"season_avg":{"PTS":4.3,"REB":1.1,"AST":0.6,"STL":0.3,"FG_PCT":0.395,"FG3_PCT":0.395},"vs_team_avg":{"PTS":0.0,"REB":1.5,"AST":0.5,"STL":0.5,"FG_PCT":0.0,"FG3_PCT":0.0},"deviations":{"PTS":-4.3,"REB":0.4,"AST":-0.1,"STL":0.2,"FG_PCT":-0.395,"FG3_PCT":-0.395}},{"player_id":1641739,"player_name":"Toumani Camara","team":"POR","gp":3,"season_avg":{"PTS":13.0,"REB":5.3,"AST":2.5,"STL":1.0,"FG_PCT":0.433,"FG3_PCT":0.361},"vs_team_avg":{"PTS":9.0,"REB":4.3,"AST":2.0,"STL":1.0,"FG_PCT":0.4,"FG3_PCT":0.278},"deviations":{"PTS":-4.0,"REB":-1.0,"AST":-0.5,"STL":0.0,"FG_PCT":-0.033,"FG3_PCT":-0.083}},{"player_id":1630170,"player_name":"Devin Vassell","team":"SAS","gp":3,"season_avg":{"PTS":14.6,"REB":3.9,"AST":2.4,"STL":0.9,"FG_PCT":0.444,"FG3_PCT":0.392},"vs_team_avg":{"PTS":10.7,"REB":3.0,"AST":3.3,"STL":1.7,"FG_PCT":0.379,"FG3_PCT":0.286},"deviations":{"PTS":-3.9,"REB":-0.9,"AST":0.9,"STL":0.8,"FG_PCT":-0.065,"FG3_PCT":-0.106}},{"player_id":1626171,"player_name":"Bobby Portis","team":"MIL","gp":2,"season_avg":{"PTS":13.3,"REB":6.3,"AST":1.5,"STL":0.5,"FG_PCT":0.49,"FG3_PCT":0.456},"vs_team_avg":{"PTS":9.5,"REB":9.0,"AST":1.5,"STL":0.0,"FG_PCT":0.4,"FG3_PCT":0.429},"deviations":{"PTS":-3.8,"REB":2.7,"AST":0.0,"STL":-0.5,"FG_PCT":-0.09,"FG3_PCT":-0.027}},{"player_id":1642262,"player_name":"Cody Williams","team":"UTA","gp":2,"season_avg":{"PTS":5.7,"REB":2.4,"AST":1.0,"STL":0.6,"FG_PCT":0.467,"FG3_PCT":0.219},"vs_team_avg":{"PTS":2.0,"REB":0.0,"AST":0.0,"STL":0.5,"FG_PCT":0.286,"FG3_PCT":0.0},"deviations":{"PTS":-3.7,"REB":-2.4,"AST":-1.0,"STL":-0.1,"FG_PCT":-0.181,"FG3_PCT":-0.219}},{"player_id":201567,"player_name":"Kevin Love","team":"UTA","gp":3,"season_avg":{"PTS":6.7,"REB":5.8,"AST":1.9,"STL":0.4,"FG_PCT":0.396,"FG3_PCT":0.359},"vs_team_avg":{"PTS":3.0,"REB":5.0,"AST":1.0,"STL":0.3,"FG_PCT":0.25,"FG3_PCT":0.111},"deviations":{"PTS":-3.7,"REB":-0.8,"AST":-0.9,"STL":-0.1,"FG_PCT":-0.146,"FG3_PCT":-0.248}},{"player_id":1641712,"player_name":"Rayan Rupert","team":"MEM","gp":2,"season_avg":{"PTS":3.6,"REB":2.2,"AST":0.8,"STL":0.7,"FG_PCT":0.381,"FG3_PCT":0.318},"vs_team_avg":{"PTS":0.0,"REB":1.5,"AST":1.0,"STL":2.0,"FG_PCT":0.0,"FG3_PCT":0.0},"deviations":{"PTS":-3.6,"REB":-0.7,"AST":0.2,"STL":1.3,"FG_PCT":-0.381,"FG3_PCT":-0.318}}],"label":"Wings"},"C":{"sample_size":{"total_player_games":147,"unique_players":76},"deviations":{"PTS":{"value":-1.08,"rank":2,"pctile":97},"REB":{"value":-0.44,"rank":5,"pctile":86},"AST":{"value":-0.159,"rank":6,"pctile":83},"STL":{"value":0.013,"rank":17,"pctile":45},"BLK":{"value":-0.297,"rank":1,"pctile":100},"TOV":{"value":0.037,"rank":18,"pctile":41},"FG_PCT":{"value":-0.029,"rank":10,"pctile":69},"FG3_PCT":{"value":-0.095,"rank":6,"pctile":83},"FGM":{"value":-0.249,"rank":10,"pctile":69},"FGA":{"value":-0.787,"rank":1,"pctile":100},"FG3M":{"value":-0.202,"rank":3,"pctile":93},"FG3A":{"value":-0.405,"rank":2,"pctile":97},"FTM":{"value":-0.387,"rank":2,"pctile":97},"FTA":{"value":-0.522,"rank":2,"pctile":97},"OREB":{"value":-0.139,"rank":7,"pctile":79},"DREB":{"value":-0.291,"rank":6,"pctile":83},"MIN":{"value":-0.895,"rank":3,"pctile":93}},"top_affected_players":[{"player_id":1629675,"player_name":"Naz Reid","team":"MIN","gp":2,"season_avg":{"PTS":13.9,"REB":6.4,"AST":2.4,"STL":1.0,"FG_PCT":0.467,"FG3_PCT":0.381},"vs_team_avg":{"PTS":5.0,"REB":5.0,"AST":1.5,"STL":0.5,"FG_PCT":0.211,"FG3_PCT":0.222},"deviations":{"PTS":-8.9,"REB":-1.4,"AST":-0.9,"STL":-0.5,"FG_PCT":-0.256,"FG3_PCT":-0.159}},{"player_id":1630568,"player_name":"Luka Garza","team":"BOS","gp":2,"season_avg":{"PTS":7.2,"REB":4.1,"AST":1.0,"STL":0.4,"FG_PCT":0.573,"FG3_PCT":0.442},"vs_team_avg":{"PTS":0.0,"REB":0.0,"AST":0.5,"STL":0.0,"FG_PCT":0.0,"FG3_PCT":0.0},"deviations":{"PTS":-7.2,"REB":-4.1,"AST":-0.5,"STL":-0.4,"FG_PCT":-0.573,"FG3_PCT":-0.442}},{"player_id":1626167,"player_name":"Myles Turner","team":"MIL","gp":2,"season_avg":{"PTS":12.5,"REB":5.6,"AST":1.6,"STL":0.7,"FG_PCT":0.442,"FG3_PCT":0.385},"vs_team_avg":{"PTS":5.5,"REB":7.0,"AST":0.5,"STL":0.0,"FG_PCT":0.4,"FG3_PCT":0.5},"deviations":{"PTS":-7.0,"REB":1.4,"AST":-1.1,"STL":-0.7,"FG_PCT":-0.042,"FG3_PCT":0.115}},{"player_id":1630168,"player_name":"Onyeka Okongwu","team":"ATL","gp":2,"season_avg":{"PTS":16.1,"REB":7.9,"AST":3.3,"STL":1.1,"FG_PCT":0.483,"FG3_PCT":0.385},"vs_team_avg":{"PTS":9.5,"REB":8.0,"AST":4.0,"STL":1.5,"FG_PCT":0.409,"FG3_PCT":0.0},"deviations":{"PTS":-6.6,"REB":0.1,"AST":0.7,"STL":0.4,"FG_PCT":-0.074,"FG3_PCT":-0.385}},{"player_id":203497,"player_name":"Rudy Gobert","team":"MIN","gp":2,"season_avg":{"PTS":10.8,"REB":11.5,"AST":1.7,"STL":0.8,"FG_PCT":0.7,"FG3_PCT":0.0},"vs_team_avg":{"PTS":5.5,"REB":6.5,"AST":2.0,"STL":0.0,"FG_PCT":0.714,"FG3_PCT":0.0},"deviations":{"PTS":-5.3,"REB":-5.0,"AST":0.3,"STL":-0.8,"FG_PCT":0.014,"FG3_PCT":0.0}},{"player_id":1642271,"player_name":"Kyle Filipowski","team":"UTA","gp":2,"season_avg":{"PTS":10.2,"REB":6.6,"AST":2.2,"STL":0.9,"FG_PCT":0.49,"FG3_PCT":0.333},"vs_team_avg":{"PTS":5.0,"REB":8.0,"AST":1.0,"STL":0.0,"FG_PCT":0.4,"FG3_PCT":0.0},"deviations":{"PTS":-5.2,"REB":1.4,"AST":-1.2,"STL":-0.9,"FG_PCT":-0.09,"FG3_PCT":-0.333}},{"player_id":1629655,"player_name":"Daniel Gafford","team":"DAL","gp":3,"season_avg":{"PTS":8.2,"REB":6.4,"AST":1.0,"STL":0.8,"FG_PCT":0.62,"FG3_PCT":0.0},"vs_team_avg":{"PTS":3.0,"REB":4.0,"AST":0.7,"STL":0.3,"FG_PCT":0.5,"FG3_PCT":0.0},"deviations":{"PTS":-5.2,"REB":-2.4,"AST":-0.3,"STL":-0.5,"FG_PCT":-0.12,"FG3_PCT":0.0}},{"player_id":1631096,"player_name":"Chet Holmgren","team":"OKC","gp":2,"season_avg":{"PTS":17.1,"REB":9.0,"AST":1.7,"STL":0.5,"FG_PCT":0.551,"FG3_PCT":0.346},"vs_team_avg":{"PTS":12.0,"REB":6.5,"AST":1.5,"STL":0.5,"FG_PCT":0.529,"FG3_PCT":0.5},"deviations":{"PTS":-5.1,"REB":-2.5,"AST":-0.2,"STL":0.0,"FG_PCT":-0.022,"FG3_PCT":0.154}},{"player_id":1642366,"player_name":"Quinten Post","team":"GSW","gp":3,"season_avg":{"PTS":7.6,"REB":4.1,"AST":1.4,"STL":0.4,"FG_PCT":0.438,"FG3_PCT":0.339},"vs_team_avg":{"PTS":2.7,"REB":3.3,"AST":0.3,"STL":0.3,"FG_PCT":0.444,"FG3_PCT":0.0},"deviations":{"PTS":-4.9,"REB":-0.8,"AST":-1.1,"STL":-0.1,"FG_PCT":0.006,"FG3_PCT":-0.339}},{"player_id":201567,"player_name":"Kevin Love","team":"UTA","gp":3,"season_avg":{"PTS":6.7,"REB":5.8,"AST":1.9,"STL":0.4,"FG_PCT":0.396,"FG3_PCT":0.359},"vs_team_avg":{"PTS":3.0,"REB":5.0,"AST":1.0,"STL":0.3,"FG_PCT":0.25,"FG3_PCT":0.111},"deviations":{"PTS":-3.7,"REB":-0.8,"AST":-0.9,"STL":-0.1,"FG_PCT":-0.146,"FG3_PCT":-0.248}},{"player_id":1627826,"player_name":"Ivica Zubac","team":"IND","gp":3,"season_avg":{"PTS":14.4,"REB":11.0,"AST":2.2,"STL":0.4,"FG_PCT":0.613,"FG3_PCT":0.0},"vs_team_avg":{"PTS":11.0,"REB":10.3,"AST":1.7,"STL":0.7,"FG_PCT":0.5,"FG3_PCT":0.0},"deviations":{"PTS":-3.4,"REB":-0.7,"AST":-0.5,"STL":0.3,"FG_PCT":-0.113,"FG3_PCT":0.0}},{"player_id":1642852,"player_name":"Derik Queen","team":"NOP","gp":4,"season_avg":{"PTS":12.0,"REB":7.2,"AST":3.9,"STL":1.0,"FG_PCT":0.486,"FG3_PCT":0.267},"vs_team_avg":{"PTS":9.0,"REB":8.0,"AST":5.0,"STL":0.8,"FG_PCT":0.371,"FG3_PCT":0.0},"deviations":{"PTS":-3.0,"REB":0.8,"AST":1.1,"STL":-0.2,"FG_PCT":-0.115,"FG3_PCT":-0.267}},{"player_id":1630583,"player_name":"Santi Aldama","team":"MEM","gp":3,"season_avg":{"PTS":14.0,"REB":6.7,"AST":2.9,"STL":0.9,"FG_PCT":0.479,"FG3_PCT":0.35},"vs_team_avg":{"PTS":11.3,"REB":9.0,"AST":4.7,"STL":1.0,"FG_PCT":0.324,"FG3_PCT":0.222},"deviations":{"PTS":-2.7,"REB":2.3,"AST":1.8,"STL":0.1,"FG_PCT":-0.155,"FG3_PCT":-0.128}},{"player_id":1642274,"player_name":"Yves Missi","team":"NOP","gp":4,"season_avg":{"PTS":5.6,"REB":5.5,"AST":1.2,"STL":0.3,"FG_PCT":0.534,"FG3_PCT":0.0},"vs_team_avg":{"PTS":3.0,"REB":3.5,"AST":1.0,"STL":0.0,"FG_PCT":0.417,"FG3_PCT":0.0},"deviations":{"PTS":-2.6,"REB":-2.0,"AST":-0.2,"STL":-0.3,"FG_PCT":-0.117,"FG3_PCT":0.0}},{"player_id":203939,"player_name":"Dwight Powell","team":"DAL","gp":3,"season_avg":{"PTS":3.3,"REB":3.7,"AST":1.0,"STL":0.5,"FG_PCT":0.658,"FG3_PCT":0.333},"vs_team_avg":{"PTS":0.7,"REB":3.0,"AST":0.7,"STL":0.7,"FG_PCT":0.333,"FG3_PCT":0.0},"deviations":{"PTS":-2.6,"REB":-0.7,"AST":-0.3,"STL":0.2,"FG_PCT":-0.325,"FG3_PCT":-0.333}}],"label":"Bigs"}},"scheme_fingerprint":{"synergy_defensive":[{"play_type":"Spotup","label":"Spot Up","percentile":0.586,"poss_pct":0.245,"ppp":1.042,"fg_pct":0.405,"efg_pct":0.541,"tov_pct":0.06,"score_pct":0.399,"foul_pct":0.042,"possessions":1556,"points":1622,"gp":57},{"play_type":"Transition","label":"Transition","percentile":0.483,"poss_pct":0.19,"ppp":1.123,"fg_pct":0.541,"efg_pct":0.609,"tov_pct":0.13,"score_pct":0.508,"foul_pct":0.117,"possessions":1207,"points":1355,"gp":57},{"play_type":"PRBallHandler","label":"Pick & Roll (Ball Handler)","percentile":0.759,"poss_pct":0.153,"ppp":0.863,"fg_pct":0.419,"efg_pct":0.473,"tov_pct":0.159,"score_pct":0.389,"foul_pct":0.088,"possessions":969,"points":836,"gp":57},{"play_type":"Isolation","label":"Isolation","percentile":0.483,"poss_pct":0.085,"ppp":0.937,"fg_pct":0.405,"efg_pct":0.446,"tov_pct":0.078,"score_pct":0.442,"foul_pct":0.141,"possessions":538,"points":504,"gp":57},{"play_type":"Cut","label":"Cut","percentile":0.034,"poss_pct":0.077,"ppp":1.418,"fg_pct":0.736,"efg_pct":0.736,"tov_pct":0.053,"score_pct":0.715,"foul_pct":0.133,"possessions":488,"points":692,"gp":57},{"play_type":"Misc","label":"Misc","percentile":0.172,"poss_pct":0.055,"ppp":0.551,"fg_pct":0.438,"efg_pct":0.5,"tov_pct":0.568,"score_pct":0.273,"foul_pct":0.026,"possessions":352,"points":194,"gp":57},{"play_type":"OffRebound","label":"Putbacks","percentile":0.483,"poss_pct":0.05,"ppp":1.107,"fg_pct":0.588,"efg_pct":0.594,"tov_pct":0.095,"score_pct":0.558,"foul_pct":0.085,"possessions":317,"points":351,"gp":57},{"play_type":"PRRollMan","label":"Pick & Roll (Roll Man)","percentile":0.0,"poss_pct":0.045,"ppp":1.269,"fg_pct":0.603,"efg_pct":0.682,"tov_pct":0.07,"score_pct":0.584,"foul_pct":0.119,"possessions":286,"points":363,"gp":57},{"play_type":"PRRollMan","label":"Pick & Roll (Roll Man)","percentile":0.0,"poss_pct":0.045,"ppp":1.269,"fg_pct":0.603,"efg_pct":0.682,"tov_pct":0.07,"score_pct":0.584,"foul_pct":0.119,"possessions":286,"points":363,"gp":57},{"play_type":"Handoff","label":"Handoff","percentile":0.034,"poss_pct":0.036,"ppp":1.083,"fg_pct":0.456,"efg_pct":0.559,"tov_pct":0.083,"score_pct":0.447,"foul_pct":0.075,"possessions":228,"points":247,"gp":57},{"play_type":"OffScreen","label":"Off Screen","percentile":0.931,"poss_pct":0.033,"ppp":0.861,"fg_pct":0.347,"efg_pct":0.422,"tov_pct":0.087,"score_pct":0.365,"foul_pct":0.082,"possessions":208,"points":179,"gp":57},{"play_type":"Postup","label":"Post Up","percentile":0.862,"poss_pct":0.031,"ppp":0.919,"fg_pct":0.489,"efg_pct":0.489,"tov_pct":0.173,"score_pct":0.472,"foul_pct":0.117,"possessions":197,"points":181,"gp":57}],"contest_profile":{"overall":{"d_fg_pct":0.486,"normal_fg_pct":0.467,"pct_plusminus":0.018,"d_fgm":2557,"d_fga":5263,"freq":1.0,"gp":60},"3_pointers":{"d_fg_pct":0.363,"normal_fg_pct":0.357,"pct_plusminus":0.006,"d_fgm":795,"d_fga":2192,"freq":0.416,"gp":60},"less_than_6ft":{"d_fg_pct":0.676,"normal_fg_pct":0.631,"pct_plusminus":0.045,"d_fgm":1165,"d_fga":1723,"freq":0.327,"gp":60},"greater_than_15ft":{"d_fg_pct":0.376,"normal_fg_pct":0.365,"pct_plusminus":0.012,"d_fgm":976,"d_fga":2594,"freq":0.493,"gp":60}},"hustle":{"contested_shots":36.8,"contested_shots_2pt":22.4,"contested_shots_3pt":14.5,"deflections":17.1,"charges_drawn":0.8,"screen_assists":8.7,"loose_balls_def":2.4,"def_box_outs":3.7,"gp":60}},"insights":[{"type":"three_point_impact","severity":"medium","text":"Opposing guards shoot 3.6% worse from three, #8 in the NBA."},{"type":"shooting_impact","severity":"medium","text":"Opposing bigs shoot 2.9% worse from the field, #10 in the NBA."},{"type":"three_point_impact","severity":"medium","text":"Opposing bigs shoot 9.5% worse from three, #6 in the NBA."},{"type":"scheme_strength","severity":"medium","text":"Ranks in the 75th percentile defending Pick & Roll (Ball Handler) plays (0.86 PPP allowed)."}]}